odoo/addons/sale_multi_operating_unit/README.rst
odoo/addons/sale_multi_operating_unit/__init__.py
odoo/addons/sale_multi_operating_unit/__manifest__.py
odoo/addons/sale_multi_operating_unit/i18n/it.po
odoo/addons/sale_multi_operating_unit/i18n/pt.po
odoo/addons/sale_multi_operating_unit/i18n/sale_multi_operating_unit.pot
odoo/addons/sale_multi_operating_unit/models/__init__.py
odoo/addons/sale_multi_operating_unit/models/crm_lead.py
odoo/addons/sale_multi_operating_unit/models/res_company.py
odoo/addons/sale_multi_operating_unit/models/sale_order.py
odoo/addons/sale_multi_operating_unit/models/sale_order_quote.py
odoo/addons/sale_multi_operating_unit/models/sale_order_quote_line.py
odoo/addons/sale_multi_operating_unit/readme/CONTRIBUTORS.rst
odoo/addons/sale_multi_operating_unit/readme/CREDITS.rst
odoo/addons/sale_multi_operating_unit/readme/DESCRIPTION.rst
odoo/addons/sale_multi_operating_unit/readme/USAGE.rst
odoo/addons/sale_multi_operating_unit/security/ir.model.access.csv
odoo/addons/sale_multi_operating_unit/security/ir_rule.xml
odoo/addons/sale_multi_operating_unit/static/description/icon.png
odoo/addons/sale_multi_operating_unit/static/description/index.html
odoo/addons/sale_multi_operating_unit/tests/__init__.py
odoo/addons/sale_multi_operating_unit/tests/test_sale_multi_operating_unit.py
odoo/addons/sale_multi_operating_unit/views/res_company.xml
odoo/addons/sale_multi_operating_unit/views/sale_order_view.xml
odoo12_addon_sale_multi_operating_unit-12.0.1.0.0.99.dev37.dist-info/METADATA
odoo12_addon_sale_multi_operating_unit-12.0.1.0.0.99.dev37.dist-info/WHEEL
odoo12_addon_sale_multi_operating_unit-12.0.1.0.0.99.dev37.dist-info/top_level.txt
odoo12_addon_sale_multi_operating_unit-12.0.1.0.0.99.dev37.dist-info/RECORD
