Metadata-Version: 2.1
Name: odoo12-addon-sale-multi-operating-unit
Version: 12.0.1.0.0.99.dev37
Summary: Allow a unit to request internal quotes to another
Home-page: https://github.com/OCA/operating-unit
Author: Open Source Integrators, Serpent Consulting Services Pvt. Ltd., Odoo Community Association (OCA)
Author-email: support@odoo-community.org
License: AGPL-3
Platform: UNKNOWN
Classifier: Programming Language :: Python
Classifier: Framework :: Odoo
Classifier: Framework :: Odoo :: 12.0
Classifier: License :: OSI Approved :: GNU Affero General Public License v3
Classifier: Development Status :: 4 - Beta
Requires-Python: >=3.5
Requires-Dist: odoo12-addon-product-operating-unit
Requires-Dist: odoo12-addon-res-partner-operating-unit
Requires-Dist: odoo12-addon-sale-operating-unit
Requires-Dist: odoo <12.1dev,>=12.0a
